__init__.py
pandas_dataset_handler.py
pandas_dataset_handler-0.2.13.22.dist-info/LICENSE
pandas_dataset_handler-0.2.13.22.dist-info/METADATA
pandas_dataset_handler-0.2.13.22.dist-info/WHEEL
pandas_dataset_handler-0.2.13.22.dist-info/top_level.txt
pandas_dataset_handler-0.2.13.22.dist-info/RECORD
