Metadata-Version: 2.1
Name: pandas-dataset-handler
Version: 0.2.13.22
Summary: A tool to process and export datasets in various formats including ORC, Parquet, XML, JSON, HTML, CSV, HDF5, XLSX and Markdown.
Home-page: https://github.com/jorgecardona/pandas-dataset-handler
Author: Jorge Cardona
Classifier: Programming Language :: Python :: 3
Classifier: License :: OSI Approved :: MIT License
Classifier: Operating System :: OS Independent
Requires-Python: >=3.6
License-File: LICENSE
Requires-Dist: pandas
Requires-Dist: pyarrow
Requires-Dist: pyorc
Requires-Dist: lxml
Requires-Dist: tables
Requires-Dist: openpyxl
